{"BlockId":-4,"CommitResultDate":"2022-08-10T14:25:24.349Z","Condition":"Combined Feedback","EndInteractionDate":"2022-08-10T14:25:13.517Z","ExpectedResultLayer":"7","ExpectedResultNumber":"169","LayerNumberConfiguration":[133,135,139,146,141,137,169],"ProbandId":13,"ProvidedResultLayer":"7","ProvidedResultNumber":"169","StartDate":"2022-08-10T14:23:19.373Z","Training":true,"TrialId":0,"level":"results"}
{"BlockId":-4,"CommitResultDate":"2022-08-10T14:26:49.090Z","Condition":"Combined Feedback","EndInteractionDate":"2022-08-10T14:26:43.498Z","ExpectedResultLayer":"1","ExpectedResultNumber":"158","LayerNumberConfiguration":[158,127,151,142,133,143,147],"ProbandId":13,"ProvidedResultLayer":"3","ProvidedResultNumber":"151","StartDate":"2022-08-10T14:25:24.350Z","Training":true,"TrialId":1,"level":"results"}
{"BlockId":-3,"CommitResultDate":"2022-08-10T14:27:54.283Z","Condition":"Visual Feedback","EndInteractionDate":"2022-08-10T14:27:48.414Z","ExpectedResultLayer":"2","ExpectedResultNumber":"149","LayerNumberConfiguration":[139,149,142,144,140,147,141],"ProbandId":13,"ProvidedResultLayer":"2","ProvidedResultNumber":"149","StartDate":"2022-08-10T14:27:03.637Z","Training":true,"TrialId":0,"level":"results"}
{"BlockId":-3,"CommitResultDate":"2022-08-10T14:28:43.107Z","Condition":"Visual Feedback","EndInteractionDate":"2022-08-10T14:28:38.123Z","ExpectedResultLayer":"6","ExpectedResultNumber":"159","LayerNumberConfiguration":[142,127,131,150,157,159,134],"ProbandId":13,"ProvidedResultLayer":"6","ProvidedResultNumber":"159","StartDate":"2022-08-10T14:27:54.284Z","Training":true,"TrialId":1,"level":"results"}
{"BlockId":-2,"CommitResultDate":"2022-08-10T14:29:43.658Z","Condition":"Tactile Feedback","EndInteractionDate":"2022-08-10T14:29:38.042Z","ExpectedResultLayer":"1","ExpectedResultNumber":"154","LayerNumberConfiguration":[154,145,147,146,138,141,129],"ProbandId":13,"ProvidedResultLayer":"1","ProvidedResultNumber":"154","StartDate":"2022-08-10T14:28:52.459Z","Training":true,"TrialId":0,"level":"results"}
{"BlockId":-2,"CommitResultDate":"2022-08-10T14:30:19.434Z","Condition":"Tactile Feedback","EndInteractionDate":"2022-08-10T14:30:15.290Z","ExpectedResultLayer":"2","ExpectedResultNumber":"161","LayerNumberConfiguration":[130,161,139,122,149,140,160],"ProbandId":13,"ProvidedResultLayer":"2","ProvidedResultNumber":"161","StartDate":"2022-08-10T14:29:43.660Z","Training":true,"TrialId":1,"level":"results"}
{"BlockId":-1,"CommitResultDate":"2022-08-10T14:31:25.315Z","Condition":"No Feedback","EndInteractionDate":"2022-08-10T14:31:21.510Z","ExpectedResultLayer":"2","ExpectedResultNumber":"162","LayerNumberConfiguration":[133,162,149,132,157,134,135],"ProbandId":13,"ProvidedResultLayer":"2","ProvidedResultNumber":"162","StartDate":"2022-08-10T14:30:28.811Z","Training":true,"TrialId":0,"level":"results"}
{"BlockId":-1,"CommitResultDate":"2022-08-10T14:31:58.067Z","Condition":"No Feedback","EndInteractionDate":"2022-08-10T14:31:53.387Z","ExpectedResultLayer":"5","ExpectedResultNumber":"162","LayerNumberConfiguration":[123,151,142,126,162,154,143],"ProbandId":13,"ProvidedResultLayer":"4","ProvidedResultNumber":"162","StartDate":"2022-08-10T14:31:25.315Z","Training":true,"TrialId":1,"level":"results"}
{"BlockId":0,"CommitResultDate":"2022-08-10T14:34:50.355Z","Condition":"Tactile Feedback","EndInteractionDate":"2022-08-10T14:34:43.148Z","ExpectedResultLayer":"6","ExpectedResultNumber":"153","LayerNumberConfiguration":[142,146,141,149,143,153,128],"ProbandId":13,"ProvidedResultLayer":"6","ProvidedResultNumber":"153","StartDate":"2022-08-10T14:34:06.246Z","Training":false,"TrialId":0,"level":"results"}
{"BlockId":0,"CommitResultDate":"2022-08-10T14:35:24.500Z","Condition":"Tactile Feedback","EndInteractionDate":"2022-08-10T14:35:20.763Z","ExpectedResultLayer":"3","ExpectedResultNumber":"166","LayerNumberConfiguration":[143,118,166,147,150,144,133],"ProbandId":13,"ProvidedResultLayer":"3","ProvidedResultNumber":"166","StartDate":"2022-08-10T14:34:50.356Z","Training":false,"TrialId":1,"level":"results"}
{"BlockId":0,"CommitResultDate":"2022-08-10T14:36:30.003Z","Condition":"Tactile Feedback","EndInteractionDate":"2022-08-10T14:36:24.067Z","ExpectedResultLayer":"5","ExpectedResultNumber":"149","LayerNumberConfiguration":[135,146,143,137,149,148,142],"ProbandId":13,"ProvidedResultLayer":"5","ProvidedResultNumber":"149","StartDate":"2022-08-10T14:35:24.501Z","Training":false,"TrialId":2,"level":"results"}
{"BlockId":0,"CommitResultDate":"2022-08-10T14:37:05.963Z","Condition":"Tactile Feedback","EndInteractionDate":"2022-08-10T14:36:59.667Z","ExpectedResultLayer":"6","ExpectedResultNumber":"165","LayerNumberConfiguration":[148,154,115,145,150,165,123],"ProbandId":13,"ProvidedResultLayer":"6","ProvidedResultNumber":"165","StartDate":"2022-08-10T14:36:30.004Z","Training":false,"TrialId":3,"level":"results"}
{"BlockId":0,"CommitResultDate":"2022-08-10T14:38:00.898Z","Condition":"Tactile Feedback","EndInteractionDate":"2022-08-10T14:37:56.499Z","ExpectedResultLayer":"2","ExpectedResultNumber":"158","LayerNumberConfiguration":[141,158,131,132,156,133,150],"ProbandId":13,"ProvidedResultLayer":"2","ProvidedResultNumber":"158","StartDate":"2022-08-10T14:37:05.964Z","Training":false,"TrialId":4,"level":"results"}
{"BlockId":0,"CommitResultDate":"2022-08-10T14:38:44.011Z","Condition":"Tactile Feedback","EndInteractionDate":"2022-08-10T14:38:40.339Z","ExpectedResultLayer":"1","ExpectedResultNumber":"157","LayerNumberConfiguration":[157,156,130,123,145,150,139],"ProbandId":13,"ProvidedResultLayer":"1","ProvidedResultNumber":"157","StartDate":"2022-08-10T14:38:00.899Z","Training":false,"TrialId":5,"level":"results"}
{"BlockId":0,"CommitResultDate":"2022-08-10T14:39:27.899Z","Condition":"Tactile Feedback","EndInteractionDate":"2022-08-10T14:39:23.107Z","ExpectedResultLayer":"1","ExpectedResultNumber":"158","LayerNumberConfiguration":[158,149,154,127,134,135,143],"ProbandId":13,"ProvidedResultLayer":"1","ProvidedResultNumber":"158","StartDate":"2022-08-10T14:38:44.012Z","Training":false,"TrialId":6,"level":"results"}
{"BlockId":0,"CommitResultDate":"2022-08-10T14:40:12.659Z","Condition":"Tactile Feedback","EndInteractionDate":"2022-08-10T14:40:07.899Z","ExpectedResultLayer":"2","ExpectedResultNumber":"158","LayerNumberConfiguration":[127,158,152,144,133,145,142],"ProbandId":13,"ProvidedResultLayer":"2","ProvidedResultNumber":"158","StartDate":"2022-08-10T14:39:27.900Z","Training":false,"TrialId":7,"level":"results"}
{"BlockId":0,"CommitResultDate":"2022-08-10T14:40:53.291Z","Condition":"Tactile Feedback","EndInteractionDate":"2022-08-10T14:40:49.723Z","ExpectedResultLayer":"5","ExpectedResultNumber":"160","LayerNumberConfiguration":[148,130,154,145,160,132,131],"ProbandId":13,"ProvidedResultLayer":"5","ProvidedResultNumber":"160","StartDate":"2022-08-10T14:40:12.660Z","Training":false,"TrialId":8,"level":"results"}
{"BlockId":0,"CommitResultDate":"2022-08-10T14:41:28.947Z","Condition":"Tactile Feedback","EndInteractionDate":"2022-08-10T14:41:25.187Z","ExpectedResultLayer":"1","ExpectedResultNumber":"169","LayerNumberConfiguration":[169,137,130,135,126,164,139],"ProbandId":13,"ProvidedResultLayer":"1","ProvidedResultNumber":"169","StartDate":"2022-08-10T14:40:53.292Z","Training":false,"TrialId":9,"level":"results"}
{"BlockId":0,"CommitResultDate":"2022-08-10T14:41:57.187Z","Condition":"Tactile Feedback","EndInteractionDate":"2022-08-10T14:41:53.099Z","ExpectedResultLayer":"7","ExpectedResultNumber":"152","LayerNumberConfiguration":[141,148,138,147,135,139,152],"ProbandId":13,"ProvidedResultLayer":"7","ProvidedResultNumber":"152","StartDate":"2022-08-10T14:41:28.948Z","Training":false,"TrialId":10,"level":"results"}
{"BlockId":0,"CommitResultDate":"2022-08-10T14:42:35.947Z","Condition":"Tactile Feedback","EndInteractionDate":"2022-08-10T14:42:32.107Z","ExpectedResultLayer":"6","ExpectedResultNumber":"157","LayerNumberConfiguration":[133,129,145,146,147,157,148],"ProbandId":13,"ProvidedResultLayer":"6","ProvidedResultNumber":"157","StartDate":"2022-08-10T14:41:57.188Z","Training":false,"TrialId":11,"level":"results"}
{"BlockId":0,"CommitResultDate":"2022-08-10T14:43:22.475Z","Condition":"Tactile Feedback","EndInteractionDate":"2022-08-10T14:43:18.795Z","ExpectedResultLayer":"3","ExpectedResultNumber":"154","LayerNumberConfiguration":[142,151,154,137,141,147,128],"ProbandId":13,"ProvidedResultLayer":"3","ProvidedResultNumber":"154","StartDate":"2022-08-10T14:42:35.949Z","Training":false,"TrialId":12,"level":"results"}
{"BlockId":0,"CommitResultDate":"2022-08-10T14:43:58.507Z","Condition":"Tactile Feedback","EndInteractionDate":"2022-08-10T14:43:55.603Z","ExpectedResultLayer":"7","ExpectedResultNumber":"160","LayerNumberConfiguration":[143,142,139,144,145,130,160],"ProbandId":13,"ProvidedResultLayer":"7","ProvidedResultNumber":"160","StartDate":"2022-08-10T14:43:22.475Z","Training":false,"TrialId":13,"level":"results"}
{"BlockId":0,"CommitResultDate":"2022-08-10T14:44:47.884Z","Condition":"Tactile Feedback","EndInteractionDate":"2022-08-10T14:44:44.676Z","ExpectedResultLayer":"2","ExpectedResultNumber":"153","LayerNumberConfiguration":[134,153,145,133,147,149,139],"ProbandId":13,"ProvidedResultLayer":"2","ProvidedResultNumber":"153","StartDate":"2022-08-10T14:43:58.508Z","Training":false,"TrialId":14,"level":"results"}
{"BlockId":0,"CommitResultDate":"2022-08-10T14:45:11.869Z","Condition":"Tactile Feedback","EndInteractionDate":"2022-08-10T14:45:08.820Z","ExpectedResultLayer":"5","ExpectedResultNumber":"152","LayerNumberConfiguration":[132,143,151,147,152,141,135],"ProbandId":13,"ProvidedResultLayer":"5","ProvidedResultNumber":"152","StartDate":"2022-08-10T14:44:47.884Z","Training":false,"TrialId":15,"level":"results"}
{"BlockId":0,"CommitResultDate":"2022-08-10T14:45:45.892Z","Condition":"Tactile Feedback","EndInteractionDate":"2022-08-10T14:45:42.060Z","ExpectedResultLayer":"7","ExpectedResultNumber":"172","LayerNumberConfiguration":[128,120,142,157,126,155,172],"ProbandId":13,"ProvidedResultLayer":"7","ProvidedResultNumber":"172","StartDate":"2022-08-10T14:45:11.869Z","Training":false,"TrialId":16,"level":"results"}
{"BlockId":0,"CommitResultDate":"2022-08-10T14:46:25.421Z","Condition":"Tactile Feedback","EndInteractionDate":"2022-08-10T14:46:21.443Z","ExpectedResultLayer":"4","ExpectedResultNumber":"169","LayerNumberConfiguration":[139,129,148,169,134,137,144],"ProbandId":13,"ProvidedResultLayer":"4","ProvidedResultNumber":"169","StartDate":"2022-08-10T14:45:45.892Z","Training":false,"TrialId":17,"level":"results"}
{"BlockId":0,"CommitResultDate":"2022-08-10T14:47:33.723Z","Condition":"Tactile Feedback","EndInteractionDate":"2022-08-10T14:47:29.755Z","ExpectedResultLayer":"3","ExpectedResultNumber":"158","LayerNumberConfiguration":[136,141,158,153,115,152,145],"ProbandId":13,"ProvidedResultLayer":"4","ProvidedResultNumber":"158","StartDate":"2022-08-10T14:46:25.427Z","Training":false,"TrialId":18,"level":"results"}
{"BlockId":0,"CommitResultDate":"2022-08-10T14:48:29.003Z","Condition":"Tactile Feedback","EndInteractionDate":"2022-08-10T14:48:25.211Z","ExpectedResultLayer":"4","ExpectedResultNumber":"152","LayerNumberConfiguration":[151,149,131,152,147,126,144],"ProbandId":13,"ProvidedResultLayer":"4","ProvidedResultNumber":"152","StartDate":"2022-08-10T14:47:33.727Z","Training":false,"TrialId":19,"level":"results"}
{"BlockId":0,"CommitResultDate":"2022-08-10T14:49:35.959Z","Condition":"Tactile Feedback","EndInteractionDate":"2022-08-10T14:49:27.412Z","ExpectedResultLayer":"4","ExpectedResultNumber":"166","LayerNumberConfiguration":[130,127,133,166,138,149,157],"ProbandId":13,"ProvidedResultLayer":"4","ProvidedResultNumber":"166","StartDate":"2022-08-10T14:48:29.004Z","Training":false,"TrialId":20,"level":"results"}
{"BlockId":1,"CommitResultDate":"2022-08-10T14:52:53.652Z","Condition":"No Feedback","EndInteractionDate":"2022-08-10T14:50:57.220Z","ExpectedResultLayer":"7","ExpectedResultNumber":"170","LayerNumberConfiguration":[147,134,131,126,157,135,170],"ProbandId":13,"ProvidedResultLayer":"7","ProvidedResultNumber":"170","StartDate":"2022-08-10T14:50:12.228Z","Training":false,"TrialId":0,"level":"results"}
{"BlockId":1,"CommitResultDate":"2022-08-10T14:53:43.820Z","Condition":"No Feedback","EndInteractionDate":"2022-08-10T14:53:40.260Z","ExpectedResultLayer":"6","ExpectedResultNumber":"157","LayerNumberConfiguration":[124,129,133,155,156,157,148],"ProbandId":13,"ProvidedResultLayer":"6","ProvidedResultNumber":"157","StartDate":"2022-08-10T14:52:53.655Z","Training":false,"TrialId":1,"level":"results"}
{"BlockId":1,"CommitResultDate":"2022-08-10T14:54:24.588Z","Condition":"No Feedback","EndInteractionDate":"2022-08-10T14:54:20.964Z","ExpectedResultLayer":"7","ExpectedResultNumber":"151","LayerNumberConfiguration":[141,131,145,147,146,140,151],"ProbandId":13,"ProvidedResultLayer":"5","ProvidedResultNumber":"147","StartDate":"2022-08-10T14:53:43.821Z","Training":false,"TrialId":2,"level":"results"}
{"BlockId":1,"CommitResultDate":"2022-08-10T14:55:04.987Z","Condition":"No Feedback","EndInteractionDate":"2022-08-10T14:55:00.483Z","ExpectedResultLayer":"3","ExpectedResultNumber":"153","LayerNumberConfiguration":[128,147,153,142,133,149,148],"ProbandId":13,"ProvidedResultLayer":"3","ProvidedResultNumber":"153","StartDate":"2022-08-10T14:54:24.588Z","Training":false,"TrialId":3,"level":"results"}
{"BlockId":1,"CommitResultDate":"2022-08-10T14:55:36.516Z","Condition":"No Feedback","EndInteractionDate":"2022-08-10T14:55:32.660Z","ExpectedResultLayer":"4","ExpectedResultNumber":"160","LayerNumberConfiguration":[151,136,137,160,127,147,142],"ProbandId":13,"ProvidedResultLayer":"4","ProvidedResultNumber":"160","StartDate":"2022-08-10T14:55:04.988Z","Training":false,"TrialId":4,"level":"results"}
{"BlockId":1,"CommitResultDate":"2022-08-10T14:56:08.676Z","Condition":"No Feedback","EndInteractionDate":"2022-08-10T14:56:05.236Z","ExpectedResultLayer":"1","ExpectedResultNumber":"161","LayerNumberConfiguration":[161,160,149,135,118,138,139],"ProbandId":13,"ProvidedResultLayer":"1","ProvidedResultNumber":"161","StartDate":"2022-08-10T14:55:36.517Z","Training":false,"TrialId":5,"level":"results"}
{"BlockId":1,"CommitResultDate":"2022-08-10T14:56:40.804Z","Condition":"No Feedback","EndInteractionDate":"2022-08-10T14:56:36.332Z","ExpectedResultLayer":"5","ExpectedResultNumber":"154","LayerNumberConfiguration":[142,143,144,145,154,135,139],"ProbandId":13,"ProvidedResultLayer":"5","ProvidedResultNumber":"154","StartDate":"2022-08-10T14:56:08.677Z","Training":false,"TrialId":6,"level":"results"}
{"BlockId":1,"CommitResultDate":"2022-08-10T14:57:32.627Z","Condition":"No Feedback","EndInteractionDate":"2022-08-10T14:57:26.227Z","ExpectedResultLayer":"6","ExpectedResultNumber":"152","LayerNumberConfiguration":[139,145,147,136,140,152,141],"ProbandId":13,"ProvidedResultLayer":"6","ProvidedResultNumber":"152","StartDate":"2022-08-10T14:56:40.804Z","Training":false,"TrialId":7,"level":"results"}
{"BlockId":1,"CommitResultDate":"2022-08-10T14:57:59.315Z","Condition":"No Feedback","EndInteractionDate":"2022-08-10T14:57:56.387Z","ExpectedResultLayer":"5","ExpectedResultNumber":"160","LayerNumberConfiguration":[131,139,150,140,160,128,153],"ProbandId":13,"ProvidedResultLayer":"5","ProvidedResultNumber":"160","StartDate":"2022-08-10T14:57:32.628Z","Training":false,"TrialId":8,"level":"results"}
{"BlockId":1,"CommitResultDate":"2022-08-10T14:58:25.291Z","Condition":"No Feedback","EndInteractionDate":"2022-08-10T14:58:22.995Z","ExpectedResultLayer":"3","ExpectedResultNumber":"156","LayerNumberConfiguration":[143,152,156,128,135,145,141],"ProbandId":13,"ProvidedResultLayer":"3","ProvidedResultNumber":"165","StartDate":"2022-08-10T14:57:59.316Z","Training":false,"TrialId":9,"level":"results"}
{"BlockId":1,"CommitResultDate":"2022-08-10T14:59:21.732Z","Condition":"No Feedback","EndInteractionDate":"2022-08-10T14:59:15.379Z","ExpectedResultLayer":"4","ExpectedResultNumber":"155","LayerNumberConfiguration":[129,152,150,155,132,130,153],"ProbandId":13,"ProvidedResultLayer":"7","ProvidedResultNumber":"153","StartDate":"2022-08-10T14:58:25.292Z","Training":false,"TrialId":10,"level":"results"}
{"BlockId":1,"CommitResultDate":"2022-08-10T15:00:06.884Z","Condition":"No Feedback","EndInteractionDate":"2022-08-10T15:00:01.253Z","ExpectedResultLayer":"6","ExpectedResultNumber":"148","LayerNumberConfiguration":[144,136,145,137,147,148,146],"ProbandId":13,"ProvidedResultLayer":"6","ProvidedResultNumber":"148","StartDate":"2022-08-10T14:59:21.732Z","Training":false,"TrialId":11,"level":"results"}
{"BlockId":1,"CommitResultDate":"2022-08-10T15:00:46.044Z","Condition":"No Feedback","EndInteractionDate":"2022-08-10T15:00:39.221Z","ExpectedResultLayer":"2","ExpectedResultNumber":"155","LayerNumberConfiguration":[154,155,146,133,135,142,136],"ProbandId":13,"ProvidedResultLayer":"2","ProvidedResultNumber":"155","StartDate":"2022-08-10T15:00:06.885Z","Training":false,"TrialId":12,"level":"results"}
{"BlockId":1,"CommitResultDate":"2022-08-10T15:01:35.997Z","Condition":"No Feedback","EndInteractionDate":"2022-08-10T15:01:33.076Z","ExpectedResultLayer":"5","ExpectedResultNumber":"155","LayerNumberConfiguration":[132,152,125,151,155,133,153],"ProbandId":13,"ProvidedResultLayer":"5","ProvidedResultNumber":"155","StartDate":"2022-08-10T15:00:46.045Z","Training":false,"TrialId":13,"level":"results"}
{"BlockId":1,"CommitResultDate":"2022-08-10T15:02:15.669Z","Condition":"No Feedback","EndInteractionDate":"2022-08-10T15:02:12.380Z","ExpectedResultLayer":"2","ExpectedResultNumber":"154","LayerNumberConfiguration":[145,154,144,141,127,137,152],"ProbandId":13,"ProvidedResultLayer":"2","ProvidedResultNumber":"154","StartDate":"2022-08-10T15:01:35.997Z","Training":false,"TrialId":14,"level":"results"}
{"BlockId":1,"CommitResultDate":"2022-08-10T15:03:13.076Z","Condition":"No Feedback","EndInteractionDate":"2022-08-10T15:02:54.436Z","ExpectedResultLayer":"7","ExpectedResultNumber":"156","LayerNumberConfiguration":[136,152,132,145,154,125,156],"ProbandId":13,"ProvidedResultLayer":"6","ProvidedResultNumber":"156","StartDate":"2022-08-10T15:02:15.670Z","Training":false,"TrialId":15,"level":"results"}
{"BlockId":1,"CommitResultDate":"2022-08-10T15:03:48.861Z","Condition":"No Feedback","EndInteractionDate":"2022-08-10T15:03:45.612Z","ExpectedResultLayer":"1","ExpectedResultNumber":"154","LayerNumberConfiguration":[154,150,121,146,130,151,148],"ProbandId":13,"ProvidedResultLayer":"1","ProvidedResultNumber":"154","StartDate":"2022-08-10T15:03:13.077Z","Training":false,"TrialId":16,"level":"results"}
{"BlockId":1,"CommitResultDate":"2022-08-10T15:04:28.500Z","Condition":"No Feedback","EndInteractionDate":"2022-08-10T15:04:23.004Z","ExpectedResultLayer":"3","ExpectedResultNumber":"160","LayerNumberConfiguration":[124,158,160,140,141,132,146],"ProbandId":13,"ProvidedResultLayer":"3","ProvidedResultNumber":"160","StartDate":"2022-08-10T15:03:48.861Z","Training":false,"TrialId":17,"level":"results"}
{"BlockId":1,"CommitResultDate":"2022-08-10T15:05:14.069Z","Condition":"No Feedback","EndInteractionDate":"2022-08-10T15:05:10.844Z","ExpectedResultLayer":"2","ExpectedResultNumber":"162","LayerNumberConfiguration":[145,162,146,138,142,147,120],"ProbandId":13,"ProvidedResultLayer":"2","ProvidedResultNumber":"162","StartDate":"2022-08-10T15:04:28.501Z","Training":false,"TrialId":18,"level":"results"}
{"BlockId":1,"CommitResultDate":"2022-08-10T15:05:55.548Z","Condition":"No Feedback","EndInteractionDate":"2022-08-10T15:05:51.172Z","ExpectedResultLayer":"4","ExpectedResultNumber":"163","LayerNumberConfiguration":[137,139,143,163,145,147,126],"ProbandId":13,"ProvidedResultLayer":"4","ProvidedResultNumber":"163","StartDate":"2022-08-10T15:05:14.069Z","Training":false,"TrialId":19,"level":"results"}
{"BlockId":1,"CommitResultDate":"2022-08-10T15:06:40.524Z","Condition":"No Feedback","EndInteractionDate":"2022-08-10T15:06:37.236Z","ExpectedResultLayer":"1","ExpectedResultNumber":"157","LayerNumberConfiguration":[157,150,117,149,136,141,151],"ProbandId":13,"ProvidedResultLayer":"1","ProvidedResultNumber":"157","StartDate":"2022-08-10T15:05:55.549Z","Training":false,"TrialId":20,"level":"results"}
{"BlockId":2,"CommitResultDate":"2022-08-10T15:09:24.676Z","Condition":"Visual Feedback","EndInteractionDate":"2022-08-10T15:09:21.124Z","ExpectedResultLayer":"6","ExpectedResultNumber":"161","LayerNumberConfiguration":[135,144,153,133,149,161,125],"ProbandId":13,"ProvidedResultLayer":"6","ProvidedResultNumber":"161","StartDate":"2022-08-10T15:08:41.292Z","Training":false,"TrialId":0,"level":"results"}
{"BlockId":2,"CommitResultDate":"2022-08-10T15:10:00.068Z","Condition":"Visual Feedback","EndInteractionDate":"2022-08-10T15:09:56.780Z","ExpectedResultLayer":"5","ExpectedResultNumber":"159","LayerNumberConfiguration":[129,144,133,147,159,150,138],"ProbandId":13,"ProvidedResultLayer":"5","ProvidedResultNumber":"159","StartDate":"2022-08-10T15:09:24.677Z","Training":false,"TrialId":1,"level":"results"}
{"BlockId":2,"CommitResultDate":"2022-08-10T15:10:27.029Z","Condition":"Visual Feedback","EndInteractionDate":"2022-08-10T15:10:24.092Z","ExpectedResultLayer":"3","ExpectedResultNumber":"155","LayerNumberConfiguration":[137,139,155,153,140,128,148],"ProbandId":13,"ProvidedResultLayer":"3","ProvidedResultNumber":"155","StartDate":"2022-08-10T15:10:00.069Z","Training":false,"TrialId":2,"level":"results"}
{"BlockId":2,"CommitResultDate":"2022-08-10T15:10:58.196Z","Condition":"Visual Feedback","EndInteractionDate":"2022-08-10T15:10:51.516Z","ExpectedResultLayer":"5","ExpectedResultNumber":"169","LayerNumberConfiguration":[147,138,154,123,169,136,133],"ProbandId":13,"ProvidedResultLayer":"5","ProvidedResultNumber":"169","StartDate":"2022-08-10T15:10:27.029Z","Training":false,"TrialId":3,"level":"results"}
{"BlockId":2,"CommitResultDate":"2022-08-10T15:11:29.269Z","Condition":"Visual Feedback","EndInteractionDate":"2022-08-10T15:11:25.205Z","ExpectedResultLayer":"7","ExpectedResultNumber":"153","LayerNumberConfiguration":[134,140,139,145,151,138,153],"ProbandId":13,"ProvidedResultLayer":"7","ProvidedResultNumber":"153","StartDate":"2022-08-10T15:10:58.197Z","Training":false,"TrialId":4,"level":"results"}
{"BlockId":2,"CommitResultDate":"2022-08-10T15:12:52.525Z","Condition":"Visual Feedback","EndInteractionDate":"2022-08-10T15:12:44.557Z","ExpectedResultLayer":"6","ExpectedResultNumber":"153","LayerNumberConfiguration":[146,152,133,151,138,153,129],"ProbandId":13,"ProvidedResultLayer":"6","ProvidedResultNumber":"153","StartDate":"2022-08-10T15:11:29.269Z","Training":false,"TrialId":5,"level":"results"}
{"BlockId":2,"CommitResultDate":"2022-08-10T15:13:26.549Z","Condition":"Visual Feedback","EndInteractionDate":"2022-08-10T15:13:22.749Z","ExpectedResultLayer":"3","ExpectedResultNumber":"165","LayerNumberConfiguration":[130,137,165,143,142,136,147],"ProbandId":13,"ProvidedResultLayer":"3","ProvidedResultNumber":"165","StartDate":"2022-08-10T15:12:52.528Z","Training":false,"TrialId":6,"level":"results"}
{"BlockId":2,"CommitResultDate":"2022-08-10T15:14:03.573Z","Condition":"Visual Feedback","EndInteractionDate":"2022-08-10T15:14:00.085Z","ExpectedResultLayer":"1","ExpectedResultNumber":"164","LayerNumberConfiguration":[164,145,139,117,159,131,146],"ProbandId":13,"ProvidedResultLayer":"1","ProvidedResultNumber":"164","StartDate":"2022-08-10T15:13:26.550Z","Training":false,"TrialId":7,"level":"results"}
{"BlockId":2,"CommitResultDate":"2022-08-10T15:14:39.453Z","Condition":"Visual Feedback","EndInteractionDate":"2022-08-10T15:14:34.061Z","ExpectedResultLayer":"6","ExpectedResultNumber":"158","LayerNumberConfiguration":[149,132,157,145,126,158,134],"ProbandId":13,"ProvidedResultLayer":"6","ProvidedResultNumber":"158","StartDate":"2022-08-10T15:14:03.574Z","Training":false,"TrialId":8,"level":"results"}
{"BlockId":2,"CommitResultDate":"2022-08-10T15:15:23.053Z","Condition":"Visual Feedback","EndInteractionDate":"2022-08-10T15:15:19.485Z","ExpectedResultLayer":"2","ExpectedResultNumber":"161","LayerNumberConfiguration":[125,161,142,146,144,141,143],"ProbandId":13,"ProvidedResultLayer":"2","ProvidedResultNumber":"161","StartDate":"2022-08-10T15:14:39.454Z","Training":false,"TrialId":9,"level":"results"}
{"BlockId":2,"CommitResultDate":"2022-08-10T15:15:55.725Z","Condition":"Visual Feedback","EndInteractionDate":"2022-08-10T15:15:52.165Z","ExpectedResultLayer":"2","ExpectedResultNumber":"157","LayerNumberConfiguration":[148,157,133,147,142,139,134],"ProbandId":13,"ProvidedResultLayer":"2","ProvidedResultNumber":"157","StartDate":"2022-08-10T15:15:23.053Z","Training":false,"TrialId":10,"level":"results"}
{"BlockId":2,"CommitResultDate":"2022-08-10T15:16:30.077Z","Condition":"Visual Feedback","EndInteractionDate":"2022-08-10T15:16:26.397Z","ExpectedResultLayer":"3","ExpectedResultNumber":"157","LayerNumberConfiguration":[143,137,157,141,146,138,139],"ProbandId":13,"ProvidedResultLayer":"3","ProvidedResultNumber":"157","StartDate":"2022-08-10T15:15:55.725Z","Training":false,"TrialId":11,"level":"results"}
{"BlockId":2,"CommitResultDate":"2022-08-10T15:16:58.925Z","Condition":"Visual Feedback","EndInteractionDate":"2022-08-10T15:16:55.669Z","ExpectedResultLayer":"2","ExpectedResultNumber":"166","LayerNumberConfiguration":[128,166,144,121,131,151,159],"ProbandId":13,"ProvidedResultLayer":"2","ProvidedResultNumber":"166","StartDate":"2022-08-10T15:16:30.077Z","Training":false,"TrialId":12,"level":"results"}
{"BlockId":2,"CommitResultDate":"2022-08-10T15:17:28.765Z","Condition":"Visual Feedback","EndInteractionDate":"2022-08-10T15:17:25.181Z","ExpectedResultLayer":"4","ExpectedResultNumber":"159","LayerNumberConfiguration":[151,154,129,159,120,131,156],"ProbandId":13,"ProvidedResultLayer":"4","ProvidedResultNumber":"159","StartDate":"2022-08-10T15:16:58.925Z","Training":false,"TrialId":13,"level":"results"}
{"BlockId":2,"CommitResultDate":"2022-08-10T15:17:58.389Z","Condition":"Visual Feedback","EndInteractionDate":"2022-08-10T15:17:55.117Z","ExpectedResultLayer":"4","ExpectedResultNumber":"157","LayerNumberConfiguration":[144,138,136,157,139,152,135],"ProbandId":13,"ProvidedResultLayer":"4","ProvidedResultNumber":"157","StartDate":"2022-08-10T15:17:28.766Z","Training":false,"TrialId":14,"level":"results"}
{"BlockId":2,"CommitResultDate":"2022-08-10T15:18:53.925Z","Condition":"Visual Feedback","EndInteractionDate":"2022-08-10T15:18:50.661Z","ExpectedResultLayer":"4","ExpectedResultNumber":"161","LayerNumberConfiguration":[151,128,133,161,149,146,132],"ProbandId":13,"ProvidedResultLayer":"4","ProvidedResultNumber":"161","StartDate":"2022-08-10T15:17:58.390Z","Training":false,"TrialId":15,"level":"results"}
{"BlockId":2,"CommitResultDate":"2022-08-10T15:19:26.901Z","Condition":"Visual Feedback","EndInteractionDate":"2022-08-10T15:19:23.974Z","ExpectedResultLayer":"5","ExpectedResultNumber":"152","LayerNumberConfiguration":[132,139,147,136,152,150,144],"ProbandId":13,"ProvidedResultLayer":"5","ProvidedResultNumber":"152","StartDate":"2022-08-10T15:18:53.925Z","Training":false,"TrialId":16,"level":"results"}
{"BlockId":2,"CommitResultDate":"2022-08-10T15:20:08.165Z","Condition":"Visual Feedback","EndInteractionDate":"2022-08-10T15:20:04.532Z","ExpectedResultLayer":"7","ExpectedResultNumber":"161","LayerNumberConfiguration":[145,138,149,133,139,135,161],"ProbandId":13,"ProvidedResultLayer":"7","ProvidedResultNumber":"161","StartDate":"2022-08-10T15:19:26.901Z","Training":false,"TrialId":17,"level":"results"}
{"BlockId":2,"CommitResultDate":"2022-08-10T15:20:32.469Z","Condition":"Visual Feedback","EndInteractionDate":"2022-08-10T15:20:28.597Z","ExpectedResultLayer":"1","ExpectedResultNumber":"151","LayerNumberConfiguration":[151,141,147,138,131,148,145],"ProbandId":13,"ProvidedResultLayer":"1","ProvidedResultNumber":"151","StartDate":"2022-08-10T15:20:08.165Z","Training":false,"TrialId":18,"level":"results"}
{"BlockId":2,"CommitResultDate":"2022-08-10T15:21:01.549Z","Condition":"Visual Feedback","EndInteractionDate":"2022-08-10T15:20:58.557Z","ExpectedResultLayer":"7","ExpectedResultNumber":"149","LayerNumberConfiguration":[133,147,139,141,145,148,149],"ProbandId":13,"ProvidedResultLayer":"7","ProvidedResultNumber":"149","StartDate":"2022-08-10T15:20:32.470Z","Training":false,"TrialId":19,"level":"results"}
{"BlockId":2,"CommitResultDate":"2022-08-10T15:21:32.381Z","Condition":"Visual Feedback","EndInteractionDate":"2022-08-10T15:21:29.653Z","ExpectedResultLayer":"1","ExpectedResultNumber":"155","LayerNumberConfiguration":[155,142,139,143,144,140,141],"ProbandId":13,"ProvidedResultLayer":"1","ProvidedResultNumber":"155","StartDate":"2022-08-10T15:21:01.550Z","Training":false,"TrialId":20,"level":"results"}
{"BlockId":3,"CommitResultDate":"2022-08-10T15:23:44.301Z","Condition":"Combined Feedback","EndInteractionDate":"2022-08-10T15:23:41.205Z","ExpectedResultLayer":"1","ExpectedResultNumber":"155","LayerNumberConfiguration":[155,140,154,151,125,131,144],"ProbandId":13,"ProvidedResultLayer":"1","ProvidedResultNumber":"155","StartDate":"2022-08-10T15:23:10.597Z","Training":false,"TrialId":0,"level":"results"}
{"BlockId":3,"CommitResultDate":"2022-08-10T15:24:28.926Z","Condition":"Combined Feedback","EndInteractionDate":"2022-08-10T15:24:25.549Z","ExpectedResultLayer":"5","ExpectedResultNumber":"180","LayerNumberConfiguration":[128,131,141,139,180,149,132],"ProbandId":13,"ProvidedResultLayer":"5","ProvidedResultNumber":"180","StartDate":"2022-08-10T15:23:44.302Z","Training":false,"TrialId":1,"level":"results"}
{"BlockId":3,"CommitResultDate":"2022-08-10T15:24:56.277Z","Condition":"Combined Feedback","EndInteractionDate":"2022-08-10T15:24:53.557Z","ExpectedResultLayer":"2","ExpectedResultNumber":"152","LayerNumberConfiguration":[149,152,143,127,144,145,141],"ProbandId":13,"ProvidedResultLayer":"2","ProvidedResultNumber":"152","StartDate":"2022-08-10T15:24:28.927Z","Training":false,"TrialId":2,"level":"results"}
{"BlockId":3,"CommitResultDate":"2022-08-10T15:25:23.637Z","Condition":"Combined Feedback","EndInteractionDate":"2022-08-10T15:25:20.021Z","ExpectedResultLayer":"4","ExpectedResultNumber":"160","LayerNumberConfiguration":[107,159,149,160,148,140,137],"ProbandId":13,"ProvidedResultLayer":"4","ProvidedResultNumber":"160","StartDate":"2022-08-10T15:24:56.278Z","Training":false,"TrialId":3,"level":"results"}
{"BlockId":3,"CommitResultDate":"2022-08-10T15:25:51.621Z","Condition":"Combined Feedback","EndInteractionDate":"2022-08-10T15:25:47.957Z","ExpectedResultLayer":"3","ExpectedResultNumber":"167","LayerNumberConfiguration":[134,122,167,153,142,132,150],"ProbandId":13,"ProvidedResultLayer":"3","ProvidedResultNumber":"167","StartDate":"2022-08-10T15:25:23.638Z","Training":false,"TrialId":4,"level":"results"}
{"BlockId":3,"CommitResultDate":"2022-08-10T15:26:15.077Z","Condition":"Combined Feedback","EndInteractionDate":"2022-08-10T15:26:12.269Z","ExpectedResultLayer":"3","ExpectedResultNumber":"160","LayerNumberConfiguration":[139,140,160,147,138,133,143],"ProbandId":13,"ProvidedResultLayer":"3","ProvidedResultNumber":"160","StartDate":"2022-08-10T15:25:51.622Z","Training":false,"TrialId":5,"level":"results"}
{"BlockId":3,"CommitResultDate":"2022-08-10T15:27:00.710Z","Condition":"Combined Feedback","EndInteractionDate":"2022-08-10T15:26:56.494Z","ExpectedResultLayer":"6","ExpectedResultNumber":"155","LayerNumberConfiguration":[142,143,151,147,128,155,135],"ProbandId":13,"ProvidedResultLayer":"6","ProvidedResultNumber":"155","StartDate":"2022-08-10T15:26:15.078Z","Training":false,"TrialId":6,"level":"results"}
{"BlockId":3,"CommitResultDate":"2022-08-10T15:27:37.421Z","Condition":"Combined Feedback","EndInteractionDate":"2022-08-10T15:27:33.685Z","ExpectedResultLayer":"5","ExpectedResultNumber":"163","LayerNumberConfiguration":[144,148,130,140,163,146,129],"ProbandId":13,"ProvidedResultLayer":"5","ProvidedResultNumber":"163","StartDate":"2022-08-10T15:27:00.711Z","Training":false,"TrialId":7,"level":"results"}
{"BlockId":3,"CommitResultDate":"2022-08-10T15:28:05.917Z","Condition":"Combined Feedback","EndInteractionDate":"2022-08-10T15:28:02.957Z","ExpectedResultLayer":"1","ExpectedResultNumber":"154","LayerNumberConfiguration":[154,144,147,136,137,138,146],"ProbandId":13,"ProvidedResultLayer":"1","ProvidedResultNumber":"154","StartDate":"2022-08-10T15:27:37.421Z","Training":false,"TrialId":8,"level":"results"}
{"BlockId":3,"CommitResultDate":"2022-08-10T15:28:33.525Z","Condition":"Combined Feedback","EndInteractionDate":"2022-08-10T15:28:30.349Z","ExpectedResultLayer":"2","ExpectedResultNumber":"159","LayerNumberConfiguration":[144,159,153,138,141,133,132],"ProbandId":13,"ProvidedResultLayer":"2","ProvidedResultNumber":"159","StartDate":"2022-08-10T15:28:05.918Z","Training":false,"TrialId":9,"level":"results"}
{"BlockId":3,"CommitResultDate":"2022-08-10T15:28:58.901Z","Condition":"Combined Feedback","EndInteractionDate":"2022-08-10T15:28:56.165Z","ExpectedResultLayer":"6","ExpectedResultNumber":"154","LayerNumberConfiguration":[150,146,145,144,120,154,141],"ProbandId":13,"ProvidedResultLayer":"6","ProvidedResultNumber":"154","StartDate":"2022-08-10T15:28:33.526Z","Training":false,"TrialId":10,"level":"results"}
{"BlockId":3,"CommitResultDate":"2022-08-10T15:29:24.693Z","Condition":"Combined Feedback","EndInteractionDate":"2022-08-10T15:29:19.021Z","ExpectedResultLayer":"1","ExpectedResultNumber":"153","LayerNumberConfiguration":[153,136,149,137,138,147,141],"ProbandId":13,"ProvidedResultLayer":"1","ProvidedResultNumber":"153","StartDate":"2022-08-10T15:28:58.902Z","Training":false,"TrialId":11,"level":"results"}
{"BlockId":3,"CommitResultDate":"2022-08-10T15:29:51.622Z","Condition":"Combined Feedback","EndInteractionDate":"2022-08-10T15:29:49.208Z","ExpectedResultLayer":"7","ExpectedResultNumber":"149","LayerNumberConfiguration":[148,147,133,146,142,135,149],"ProbandId":13,"ProvidedResultLayer":"7","ProvidedResultNumber":"149","StartDate":"2022-08-10T15:29:24.694Z","Training":false,"TrialId":12,"level":"results"}
{"BlockId":3,"CommitResultDate":"2022-08-10T15:30:18.429Z","Condition":"Combined Feedback","EndInteractionDate":"2022-08-10T15:30:15.310Z","ExpectedResultLayer":"4","ExpectedResultNumber":"160","LayerNumberConfiguration":[137,150,126,160,135,151,141],"ProbandId":13,"ProvidedResultLayer":"4","ProvidedResultNumber":"160","StartDate":"2022-08-10T15:29:51.623Z","Training":false,"TrialId":13,"level":"results"}
{"BlockId":3,"CommitResultDate":"2022-08-10T15:30:42.013Z","Condition":"Combined Feedback","EndInteractionDate":"2022-08-10T15:30:39.271Z","ExpectedResultLayer":"3","ExpectedResultNumber":"154","LayerNumberConfiguration":[150,136,154,130,131,149,151],"ProbandId":13,"ProvidedResultLayer":"3","ProvidedResultNumber":"154","StartDate":"2022-08-10T15:30:18.430Z","Training":false,"TrialId":14,"level":"results"}
{"BlockId":3,"CommitResultDate":"2022-08-10T15:31:06.429Z","Condition":"Combined Feedback","EndInteractionDate":"2022-08-10T15:31:03.374Z","ExpectedResultLayer":"7","ExpectedResultNumber":"157","LayerNumberConfiguration":[149,131,152,129,133,150,157],"ProbandId":13,"ProvidedResultLayer":"7","ProvidedResultNumber":"157","StartDate":"2022-08-10T15:30:42.014Z","Training":false,"TrialId":15,"level":"results"}
{"BlockId":3,"CommitResultDate":"2022-08-10T15:31:41.550Z","Condition":"Combined Feedback","EndInteractionDate":"2022-08-10T15:31:38.750Z","ExpectedResultLayer":"6","ExpectedResultNumber":"165","LayerNumberConfiguration":[132,120,144,128,156,165,155],"ProbandId":13,"ProvidedResultLayer":"6","ProvidedResultNumber":"165","StartDate":"2022-08-10T15:31:06.430Z","Training":false,"TrialId":16,"level":"results"}
{"BlockId":3,"CommitResultDate":"2022-08-10T15:32:26.382Z","Condition":"Combined Feedback","EndInteractionDate":"2022-08-10T15:32:23.294Z","ExpectedResultLayer":"7","ExpectedResultNumber":"151","LayerNumberConfiguration":[148,129,150,136,145,141,151],"ProbandId":13,"ProvidedResultLayer":"7","ProvidedResultNumber":"151","StartDate":"2022-08-10T15:31:41.550Z","Training":false,"TrialId":17,"level":"results"}
{"BlockId":3,"CommitResultDate":"2022-08-10T15:32:50.893Z","Condition":"Combined Feedback","EndInteractionDate":"2022-08-10T15:32:47.605Z","ExpectedResultLayer":"5","ExpectedResultNumber":"159","LayerNumberConfiguration":[146,143,128,131,159,144,149],"ProbandId":13,"ProvidedResultLayer":"5","ProvidedResultNumber":"159","StartDate":"2022-08-10T15:32:26.382Z","Training":false,"TrialId":18,"level":"results"}
{"BlockId":3,"CommitResultDate":"2022-08-10T15:33:19.501Z","Condition":"Combined Feedback","EndInteractionDate":"2022-08-10T15:33:16.150Z","ExpectedResultLayer":"2","ExpectedResultNumber":"161","LayerNumberConfiguration":[151,161,133,127,143,140,145],"ProbandId":13,"ProvidedResultLayer":"2","ProvidedResultNumber":"161","StartDate":"2022-08-10T15:32:50.894Z","Training":false,"TrialId":19,"level":"results"}
{"BlockId":3,"CommitResultDate":"2022-08-10T15:34:06.198Z","Condition":"Combined Feedback","EndInteractionDate":"2022-08-10T15:34:03.118Z","ExpectedResultLayer":"4","ExpectedResultNumber":"157","LayerNumberConfiguration":[128,142,139,157,147,132,155],"ProbandId":13,"ProvidedResultLayer":"4","ProvidedResultNumber":"157","StartDate":"2022-08-10T15:33:19.502Z","Training":false,"TrialId":20,"level":"results"}
